SbtZhongwenShouce/README.md
SbtZhongwenShouce/__init__.py
SbtZhongwenShouce/__main__.py
SbtZhongwenShouce/file.epub
SbtZhongwenShouce/index.html
SbtZhongwenShouce/css/__init__.py
SbtZhongwenShouce/css/annotations.css
SbtZhongwenShouce/css/main.css
SbtZhongwenShouce/css/normalize.css
SbtZhongwenShouce/css/popup.css
SbtZhongwenShouce/font/__init__.py
SbtZhongwenShouce/font/fontello.eot
SbtZhongwenShouce/font/fontello.svg
SbtZhongwenShouce/font/fontello.ttf
SbtZhongwenShouce/font/fontello.woff
SbtZhongwenShouce/img/__init__.py
SbtZhongwenShouce/img/annotator-glyph-sprite.png
SbtZhongwenShouce/img/annotator-icon-sprite.png
SbtZhongwenShouce/img/apple-touch-icon.png
SbtZhongwenShouce/img/cancelfullscreen.png
SbtZhongwenShouce/img/close.png
SbtZhongwenShouce/img/fullscreen.png
SbtZhongwenShouce/img/loader.gif
SbtZhongwenShouce/img/menu-icon.png
SbtZhongwenShouce/img/save.png
SbtZhongwenShouce/img/saved.png
SbtZhongwenShouce/img/settings-s.png
SbtZhongwenShouce/img/settings.png
SbtZhongwenShouce/img/star.png
SbtZhongwenShouce/js/__init__.py
SbtZhongwenShouce/js/epub.js
SbtZhongwenShouce/js/epub.min.js
SbtZhongwenShouce/js/epub.min.map
SbtZhongwenShouce/js/hooks.min.js
SbtZhongwenShouce/js/hooks.min.map
SbtZhongwenShouce/js/reader.js
SbtZhongwenShouce/js/reader.js.map
SbtZhongwenShouce/js/reader.min.js
SbtZhongwenShouce/js/reader.min.map
SbtZhongwenShouce/js/hooks/__init__.py
SbtZhongwenShouce/js/hooks/extensions/__init__.py
SbtZhongwenShouce/js/hooks/extensions/highlight.js
SbtZhongwenShouce/js/libs/__init__.py
SbtZhongwenShouce/js/libs/jquery.min.js
SbtZhongwenShouce/js/libs/localforage.min.js
SbtZhongwenShouce/js/libs/screenfull.js
SbtZhongwenShouce/js/libs/screenfull.min.js
SbtZhongwenShouce/js/libs/zip.min.js
SbtZhongwenShouce/js/plugins/__init__.py
SbtZhongwenShouce/js/plugins/hypothesis.js
SbtZhongwenShouce/js/plugins/search.js
sbt_zhongwen_shouce-2024.3.3.0.dist-info/METADATA
sbt_zhongwen_shouce-2024.3.3.0.dist-info/WHEEL
sbt_zhongwen_shouce-2024.3.3.0.dist-info/entry_points.txt
sbt_zhongwen_shouce-2024.3.3.0.dist-info/top_level.txt
sbt_zhongwen_shouce-2024.3.3.0.dist-info/RECORD
